hgfind/__init__.py
hgfind/biomart-gene-coordinates.txt
hgfind/hgfind.py
hgfind-1.0.0.dist-info/LICENSE
hgfind-1.0.0.dist-info/METADATA
hgfind-1.0.0.dist-info/WHEEL
hgfind-1.0.0.dist-info/entry_points.txt
hgfind-1.0.0.dist-info/top_level.txt
hgfind-1.0.0.dist-info/RECORD
