Metadata-Version: 2.1
Name: hgfind
Version: 1.0.0
Summary: Convert a gene name to human genome coordinates
Home-page: https://github.com/mnahinkhan/hgfind
Author: Nahin Khan
Author-email: mnahinkhan@gmail.com
License: UNKNOWN
Platform: UNKNOWN
Classifier: Programming Language :: Python :: 3
Classifier: License :: OSI Approved :: MIT License
Classifier: Operating System :: OS Independent
Requires-Python: >=3.6
License-File: LICENSE
